{
  "users": [
    {
      "id": "khnghy",
      "email": "alan.tran@kyberosc.com",
      "name": "Alan Tran",
      "password": "12345"
    },
    {
      "name": "Alan Tran",
      "phone": "013655458455",
      "id": "lgTvt4Eh2",
      "avatar": ""
    },
    {
      "name": "Alan Tran",
      "phone": "(845) 482-1690",
      "id": "3EhiAu4t8r",
      "avatar": ""
    },
    {
      "name": "Alan Tran",
      "phone": "(845) 482-1690",
      "id": "SXLqpWa0E",
      "avatar": ""
    },
    {
      "name": "Alan Tran",
      "phone": "(845) 482-1690",
      "id": "Ch0chKFIX",
      "avatar": ""
    },
    {
      "name": "Alan Tran",
      "phone": "(845) 482-1690",
      "id": "1kIE51I9c",
      "avatar": [
        "public\\uploads\\881fc53a01153b5037220a3ef41ad4fd"
      ]
    },
    {
      "name": "Alan Tran",
      "phone": "(845) 482-1690",
      "id": "PR9XUG5bJ",
      "avatar": [
        "public\\uploads\\5541e7366a916c375e41bbf029ea3231"
      ]
    },
    {
      "name": "Alan Tran",
      "phone": "(845) 482-1690",
      "id": "3GYPLO5FZ",
      "avatar": ""
    },
    {
      "name": "Alan Tran ss",
      "phone": "(845) 482-1690",
      "id": "YRcJRGNcK",
      "avatar": ""
    },
    {
      "name": "Alan Tran ss",
      "phone": "(845) 482-1690",
      "id": "8ycUo0W4j",
      "avatar": ""
    },
    {
      "name": "Alan Tran",
      "phone": "013655458455",
      "id": "KNpY_Tjtt"
    },
    {
      "name": "Alan Tran",
      "phone": "013655458455",
      "id": "hm_E6rjft",
      "avatar": ""
    },
    {
      "name": "Alan Tran",
      "phone": "(845) 482-1690",
      "id": "pK8VZEpqL",
      "avatar": "uploads/bd1e1bfb7cda2919c4316a586dd1ef24"
    },
    {
      "name": "Alan Tran",
      "phone": "(845) 482-1690",
      "id": "aTjC2sDWx",
      "avatar": "uploads/74317237be8a148ce130add163f26472"
    },
    {
      "name": "f",
      "phone": "013655458455",
      "id": "JidJmBReG",
      "avatar": "uploads/f746c446d64893be4d6025580576e163"
    }
  ]
}